AUTHORS
ChangeLog
LICENSE
Makefile
README.md
build-requirements.txt
pytest.ini
requirements.txt
setup.cfg
setup.py
test-requirements.txt
.github/workflows/release.yml
.github/workflows/tests.yml
clouds/__init__.py
clouds/arguments.py
clouds/listing.py
clouds/sdk.py
clouds/shell.py
clouds/utils.py
cloudsyaml.egg-info/PKG-INFO
cloudsyaml.egg-info/SOURCES.txt
cloudsyaml.egg-info/dependency_links.txt
cloudsyaml.egg-info/entry_points.txt
cloudsyaml.egg-info/not-zip-safe
cloudsyaml.egg-info/pbr.json
cloudsyaml.egg-info/requires.txt
cloudsyaml.egg-info/top_level.txt
tests/clouds.yaml
tests/test_list.py