Metadata-Version: 2.1
Name: cloudsyaml
Version: 0.6.1
Summary: Simple library and CLI for explore the clouds.yaml
Home-page: http://github.com/itd27m01/cloudsyaml
Author: Igor Tiunov
Author-email: igortiunov@gmail.com
License: Apache License 2.0
Platform: UNKNOWN
Classifier: Development Status :: 3 - Alpha
Classifier: License :: Other/Proprietary License
Classifier: Programming Language :: Python
Classifier: Programming Language :: Python :: 3
Classifier: Programming Language :: Python :: 3.8
Classifier: Intended Audience :: Developers
Classifier: Environment :: Console
